terminalchart/__init__.py
terminalchart/__main__.py
terminalchart-1.0.0.dist-info/METADATA
terminalchart-1.0.0.dist-info/WHEEL
terminalchart-1.0.0.dist-info/top_level.txt
terminalchart-1.0.0.dist-info/RECORD
