Metadata-Version: 2.1
Name: terminalchart
Version: 1.0.0
Summary: Make chart on commanline interface.
Home-page: https://github.com/frozenstrawberries/Python/tree/master/terminalchart
Author: Muhammad Junaid Raza
Author-email: strawberriesfrozen@gmail.com
License: UNKNOWN
Platform: UNKNOWN
Classifier: Programming Language :: Python :: 3
Classifier: Operating System :: OS Independent
Requires-Python: >=3.6
